django_basin3d/__init__.py
django_basin3d/admin.py
django_basin3d/apps.py
django_basin3d/catalog.py
django_basin3d/models.py
django_basin3d/serializers.py
django_basin3d/settings.py
django_basin3d/urls.py
django_basin3d/views.py
django_basin3d/viewsets.py
django_basin3d/migrations/0001_initial.py
django_basin3d/migrations/0002_alter_attributemapping_id_alter_datasource_id.py
django_basin3d/migrations/__init__.py
django_basin3d/synthesis/__init__.py
django_basin3d/synthesis/serializers.py
django_basin3d/synthesis/viewsets.py
django_basin3d/templatetags/__init__.py
django_basin3d/templatetags/str_utils.py
django_basin3d-1.0.12.dist-info/licenses/LICENSE
django_basin3d-1.0.12.dist-info/METADATA
django_basin3d-1.0.12.dist-info/WHEEL
django_basin3d-1.0.12.dist-info/top_level.txt
django_basin3d-1.0.12.dist-info/RECORD
