Metadata-Version: 2.4
Name: django-basin3d
Version: 1.0.12
Summary: BASIN-3D Django Web Framework
Author-email: Valerie C Hendrix <vchendrix@lbl.gov>, Danielle Svehla Christianson <dschristianson@lbl.gov>, Charuleka Varadharajan <cvaradharajan@lbl.gov>
Maintainer-email: Valerie C Hendrix <vchendrix@lbl.gov>, Danielle Svehla Christianson <dschristianson@lbl.gov>
License: Broker for Assimilation, Synthesis and Integration of eNvironmental Diverse, Distributed Datasets (BASIN-3D) Copyright (c) 2019, The
Project-URL: homepage, https://github.com/BASIN-3D/django-basin3d
Project-URL: documentation, https://django-basin3d.readthedocs.io
Project-URL: repository, https://github.com/BASIN-3D
Project-URL: changelog, https://github.com/BASIN-3D/django-basin3d/blob/main/CHANGES.md
Classifier: Development Status :: 3 - Alpha
Classifier: Programming Language :: Python
Classifier: License :: OSI Approved :: BSD License
Classifier: Intended Audience :: Science/Research
Classifier: Intended Audience :: Developers
Classifier: Programming Language :: Python :: 3.8
Classifier: Programming Language :: Python :: 3.9
Classifier: Programming Language :: Python :: 3.10
Classifier: Topic :: Scientific/Engineering
Classifier: Topic :: Scientific/Engineering :: Hydrology
Requires-Python: <3.11,>=3.8
License-File: LICENSE
Requires-Dist: basin3d==1.2.0
Requires-Dist: django==4.0
Requires-Dist: djangorestframework
Requires-Dist: django-filter
Requires-Dist: markdown
Requires-Dist: pygments
Provides-Extra: dev
Requires-Dist: pytest; extra == "dev"
Requires-Dist: pytest-mypy; extra == "dev"
Requires-Dist: pytest-cov; extra == "dev"
Requires-Dist: pytest-django; extra == "dev"
Requires-Dist: flake8; extra == "dev"
Requires-Dist: types-PyYAML; extra == "dev"
Requires-Dist: types-chardet; extra == "dev"
Requires-Dist: types-cryptography; extra == "dev"
Requires-Dist: types-requests; extra == "dev"
Provides-Extra: docs
Requires-Dist: sphinx<=6.2.1; extra == "docs"
Requires-Dist: sphinx-autodoc-typehints<=1.23.0; extra == "docs"
Requires-Dist: graphviz; extra == "docs"
Requires-Dist: sphinx_rtd_theme; extra == "docs"
Requires-Dist: tomli; extra == "docs"
Requires-Dist: myst-parser; extra == "docs"
Dynamic: license-file
